auth_backends/__init__.py
auth_backends/backends.py
auth_backends/pipeline.py
auth_backends/strategies.py
auth_backends/urls.py
auth_backends/views.py
auth_backends/tests/__init__.py
auth_backends/tests/mixins.py
auth_backends/tests/test_backends.py
auth_backends/tests/test_pipeline.py
auth_backends/tests/test_strategies.py
auth_backends/tests/test_views.py
edx_auth_backends-4.6.2.dist-info/licenses/AUTHORS
edx_auth_backends-4.6.2.dist-info/licenses/LICENSE.txt
edx_auth_backends-4.6.2.dist-info/METADATA
edx_auth_backends-4.6.2.dist-info/WHEEL
edx_auth_backends-4.6.2.dist-info/top_level.txt
edx_auth_backends-4.6.2.dist-info/RECORD
