Metadata-Version: 2.4
Name: edx-auth-backends
Version: 4.6.2
Summary: Custom edX authentication backends and pipeline steps
Home-page: https://github.com/openedx/auth-backends
Author: edX
Author-email: oscm@edx.org
License: AGPL
Keywords: authentication edx
Classifier: Development Status :: 5 - Production/Stable
Classifier: Environment :: Web Environment
Classifier: Intended Audience :: Developers
Classifier: License :: OSI Approved :: GNU Affero General Public License v3
Classifier: Operating System :: OS Independent
Classifier: Programming Language :: Python :: 3
Classifier: Programming Language :: Python :: 3.11
Classifier: Programming Language :: Python :: 3.12
Classifier: Framework :: Django
Classifier: Framework :: Django :: 4.2
Classifier: Framework :: Django :: 5.2
Classifier: Topic :: Internet
License-File: LICENSE.txt
License-File: AUTHORS
Requires-Dist: Django
Requires-Dist: edx-django-utils
Requires-Dist: edx-toggles
Requires-Dist: pyjwt[crypto]>=2.1.0
Requires-Dist: six
Requires-Dist: social-auth-app-django
Requires-Dist: social-auth-core
Dynamic: author
Dynamic: author-email
Dynamic: classifier
Dynamic: description
Dynamic: home-page
Dynamic: keywords
Dynamic: license
Dynamic: license-file
Dynamic: requires-dist
Dynamic: summary
